tf1_tensorflow_object_detection_api-1.15.0.data/purelib/datasets/__init__.py
tf1_tensorflow_object_detection_api-1.15.0.data/purelib/datasets/build_imagenet_data.py
tf1_tensorflow_object_detection_api-1.15.0.data/purelib/datasets/cifar10.py
tf1_tensorflow_object_detection_api-1.15.0.data/purelib/datasets/dataset_factory.py
tf1_tensorflow_object_detection_api-1.15.0.data/purelib/datasets/dataset_utils.py
tf1_tensorflow_object_detection_api-1.15.0.data/purelib/datasets/download_and_convert_cifar10.py
tf1_tensorflow_object_detection_api-1.15.0.data/purelib/datasets/download_and_convert_flowers.py
tf1_tensorflow_object_detection_api-1.15.0.data/purelib/datasets/download_and_convert_mnist.py
tf1_tensorflow_object_detection_api-1.15.0.data/purelib/datasets/download_and_convert_visualwakewords.py
tf1_tensorflow_object_detection_api-1.15.0.data/purelib/datasets/download_and_convert_visualwakewords_lib.py
tf1_tensorflow_object_detection_api-1.15.0.data/purelib/datasets/flowers.py
tf1_tensorflow_object_detection_api-1.15.0.data/purelib/datasets/imagenet.py
tf1_tensorflow_object_detection_api-1.15.0.data/purelib/datasets/mnist.py
tf1_tensorflow_object_detection_api-1.15.0.data/purelib/datasets/preprocess_imagenet_validation_data.py
tf1_tensorflow_object_detection_api-1.15.0.data/purelib/datasets/process_bounding_boxes.py
tf1_tensorflow_object_detection_api-1.15.0.data/purelib/datasets/visualwakewords.py
tf1_tensorflow_object_detection_api-1.15.0.data/purelib/deployment/__init__.py
tf1_tensorflow_object_detection_api-1.15.0.data/purelib/deployment/model_deploy.py
tf1_tensorflow_object_detection_api-1.15.0.data/purelib/deployment/model_deploy_test.py
tf1_tensorflow_object_detection_api-1.15.0.data/purelib/nets/__init__.py
tf1_tensorflow_object_detection_api-1.15.0.data/purelib/nets/alexnet.py
tf1_tensorflow_object_detection_api-1.15.0.data/purelib/nets/alexnet_test.py
tf1_tensorflow_object_detection_api-1.15.0.data/purelib/nets/cifarnet.py
tf1_tensorflow_object_detection_api-1.15.0.dist-info/METADATA
tf1_tensorflow_object_detection_api-1.15.0.dist-info/WHEEL
tf1_tensorflow_object_detection_api-1.15.0.dist-info/top_level.txt
tf1_tensorflow_object_detection_api-1.15.0.dist-info/RECORD
